ego_blur/__init__.py
egoblur-2.0.0a2.dist-info/licenses/LICENSE
gen1/__init__.py
gen1/script/__init__.py
gen1/script/demo_ego_blur_gen1.py
gen2/__init__.py
gen2/script/__init__.py
gen2/script/demo_ego_blur_gen2.py
gen2/script/predictor.py
gen2/script/utils.py
gen2/script/detectron2/__init__.py
gen2/script/detectron2/export/__init__.py
gen2/script/detectron2/export/torchscript_patch.py
gen2/script/detectron2/structures/__init__.py
gen2/script/detectron2/structures/boxes.py
gen2/script/detectron2/structures/instances.py
gen2/script/detectron2/utils/__init__.py
gen2/script/detectron2/utils/env.py
gen2/script/detectron2/utils/utils.py
egoblur-2.0.0a2.dist-info/METADATA
egoblur-2.0.0a2.dist-info/WHEEL
egoblur-2.0.0a2.dist-info/entry_points.txt
egoblur-2.0.0a2.dist-info/top_level.txt
egoblur-2.0.0a2.dist-info/RECORD
