Metadata-Version: 2.4
Name: egoblur
Version: 2.0.0a2
Summary: Demo utilities for running EgoBlur person and license plate blurring models.
Author-email: Project Aria Team <projectaria@meta.com>
License-Expression: Apache-2.0
Project-URL: Homepage, https://www.projectaria.com/tools/egoblur
Project-URL: Documentation, https://www.projectaria.com/tools/egoblur
Project-URL: Source, https://github.com/facebookresearch/egoblur
Classifier: Programming Language :: Python :: 3
Classifier: Programming Language :: Python :: 3.9
Classifier: Programming Language :: Python :: 3.10
Classifier: Programming Language :: Python :: 3.11
Classifier: Programming Language :: Python :: 3.12
Classifier: Topic :: Multimedia :: Graphics
Classifier: Topic :: Multimedia :: Video
Classifier: Topic :: Scientific/Engineering :: Artificial Intelligence
Requires-Python: >=3.9
License-File: LICENSE
Requires-Dist: moviepy<2.0,>=1.0.3
Requires-Dist: numpy<3,>=1.24
Requires-Dist: opencv-python-headless<5,>=4.7
Requires-Dist: tqdm<5,>=4.64
Requires-Dist: torch==2.5.1
Requires-Dist: torchvision==0.20.1
Dynamic: license-file
